.hgignore
.hgtags
BerkeleyDB_issues.txt
ChangeLog
LICENSE.txt
MANIFEST.in
Makefile
README.txt
TODO.txt
TODO.txt.old
licenses.txt
pyproject.toml
setup.cfg
setup.py
setup3.py
test-full_prerelease.py
test.py
berkeleydb.egg-info/PKG-INFO
berkeleydb.egg-info/SOURCES.txt
berkeleydb.egg-info/dependency_links.txt
berkeleydb.egg-info/top_level.txt
docs/Makefile
docs/bitcoin.png
docs/bitcoin.png.asc
docs/changelog-bsddb3.rst
docs/changelog.rst
docs/conf.py
docs/db.rst
docs/dbcursor.rst
docs/dbenv.rst
docs/dblock.rst
docs/dblogcursor.rst
docs/dbsequence.rst
docs/dbsite.rst
docs/dbtxn.rst
docs/donate.rst
docs/history.rst
docs/index.rst
docs/introduction.rst
docs/license.rst
src/Module/berkeleydb.c
src/Module/berkeleydb.h
src/berkeleydb/__init__.py
src/berkeleydb/db.py
src/berkeleydb/dbrecio.py
src/berkeleydb/dbshelve.py
src/berkeleydb/dbutils.py
tests/__init__.py
tests/test_all.py
tests/test_associate.py
tests/test_basics.py
tests/test_compare.py
tests/test_compat.py
tests/test_concurrent_data_store.py
tests/test_cursor_pget_bug.py
tests/test_db.py
tests/test_dbenv.py
tests/test_dbshelve.py
tests/test_distributed_transactions.py
tests/test_early_close.py
tests/test_encryption.py
tests/test_fileid.py
tests/test_get_none.py
tests/test_heap.py
tests/test_join.py
tests/test_lock.py
tests/test_misc.py
tests/test_pickle.py
tests/test_queue.py
tests/test_recno.py
tests/test_replication.py
tests/test_sequence.py
tests/test_thread.py
tests/test_weakref.py